[
  {
    "rank": 1,
    "name": "",
    "price": "Sem preço",
    "url": "https://www.zoom.com.brjavascript:void(0)",
    "specifications": {}
  },
  {
    "rank": 2,
    "name": "",
    "price": "Sem preço",
    "url": "https://www.zoom.com.brjavascript:void(0)",
    "specifications": {}
  },
  {
    "rank": 3,
    "name": "Celulares",
    "price": "Sem preço",
    "url": "https://www.zoom.com.br/celular/iphone",
    "specifications": {}
  },
  {
    "rank": 4,
    "name": "Celulares",
    "price": "Sem preço",
    "url": "https://www.zoom.com.br/celular/iphone",
    "specifications": {}
  },
  {
    "rank": 5,
    "name": "iPhone",
    "price": "Sem preço",
    "url": "https://www.zoom.com.br/celular/iphone",
    "specifications": {}
  },
  {
    "rank": 6,
    "name": "iPhone",
    "price": "Sem preço",
    "url": "https://www.zoom.com.br/celular/iphone",
    "specifications": {}
  },
  {
    "rank": 7,
    "name": "Sem título",
    "price": "Sem preço",
    "url": null,
    "specifications": {}
  },
  {
    "rank": 8,
    "name": "TV 32 polegadas",
    "price": "Sem preço",
    "url": "https://www.zoom.com.br/tv/tamanho-32-polegadas",
    "specifications": {}
  },
  {
    "rank": 9,
    "name": "TV 32 polegadas",
    "price": "Sem preço",
    "url": "https://www.zoom.com.br/tv/tamanho-32-polegadas",
    "specifications": {}
  },
  {
    "rank": 10,
    "name": "Sem título",
    "price": "Sem preço",
    "url": null,
    "specifications": {}
  },
  {
    "rank": 11,
    "name": "Lavadora Brastemp",
    "price": "Sem preço",
    "url": "https://www.zoom.com.br/lavadora-roupas/brastemp",
    "specifications": {}
  },
  {
    "rank": 12,
    "name": "Lavadora Brastemp",
    "price": "Sem preço",
    "url": "https://www.zoom.com.br/lavadora-roupas/brastemp",
    "specifications": {}
  },
  {
    "rank": 13,
    "name": "Sem título",
    "price": "Sem preço",
    "url": null,
    "specifications": {}
  },
  {
    "rank": 14,
    "name": "Notebook  Samsung",
    "price": "Sem preço",
    "url": "https://www.zoom.com.br/notebook/samsung",
    "specifications": {}
  },
  {
    "rank": 15,
    "name": "Notebook  Samsung",
    "price": "Sem preço",
    "url": "https://www.zoom.com.br/notebook/samsung",
    "specifications": {}
  },
  {
    "rank": 16,
    "name": "Sem título",
    "price": "Sem preço",
    "url": null,
    "specifications": {}
  },
  {
    "rank": 17,
    "name": "Geladeira Electrolux",
    "price": "Sem preço",
    "url": "https://www.zoom.com.br/geladeira/electrolux",
    "specifications": {}
  },
  {
    "rank": 18,
    "name": "Geladeira Electrolux",
    "price": "Sem preço",
    "url": "https://www.zoom.com.br/geladeira/electrolux",
    "specifications": {}
  },
  {
    "rank": 19,
    "name": "Sem título",
    "price": "Sem preço",
    "url": null,
    "specifications": {}
  },
  {
    "rank": 20,
    "name": "Ar-condicionado 7.500 BTUs",
    "price": "Sem preço",
    "url": "https://www.zoom.com.br/ar-condicionado/7-500-btus",
    "specifications": {}
  },
  {
    "rank": 21,
    "name": "Ar-condicionado 7.500 BTUs",
    "price": "Sem preço",
    "url": "https://www.zoom.com.br/ar-condicionado/7-500-btus",
    "specifications": {}
  },
  {
    "rank": 22,
    "name": "Sem título",
    "price": "Sem preço",
    "url": null,
    "specifications": {}
  },
  {
    "rank": 23,
    "name": "Fogão 4 bocas",
    "price": "Sem preço",
    "url": "https://www.zoom.com.br/fogao/4-bocas",
    "specifications": {}
  },
  {
    "rank": 24,
    "name": "Fogão 4 bocas",
    "price": "Sem preço",
    "url": "https://www.zoom.com.br/fogao/4-bocas",
    "specifications": {}
  },
  {
    "rank": 25,
    "name": "Sem título",
    "price": "Sem preço",
    "url": null,
    "specifications": {}
  },
  {
    "rank": 26,
    "name": "Playstation 4",
    "price": "Sem preço",
    "url": "https://www.zoom.com.br/console-de-video-game/playstation-4",
    "specifications": {}
  },
  {
    "rank": 27,
    "name": "Playstation 4",
    "price": "Sem preço",
    "url": "https://www.zoom.com.br/console-de-video-game/playstation-4",
    "specifications": {}
  },
  {
    "rank": 28,
    "name": "Sem título",
    "price": "Sem preço",
    "url": null,
    "specifications": {}
  },
  {
    "rank": 29,
    "name": "Automóveis e Veículos",
    "price": "Sem preço",
    "url": "https://www.zoom.com.br/automoveis-e-veiculos",
    "specifications": {}
  },
  {
    "rank": 30,
    "name": "Automóveis e Veículos",
    "price": "Sem preço",
    "url": "https://www.zoom.com.br/automoveis-e-veiculos",
    "specifications": {}
  },
  {
    "rank": 31,
    "name": "Sem título",
    "price": "Sem preço",
    "url": null,
    "specifications": {}
  },
  {
    "rank": 32,
    "name": "Sem título",
    "price": "Sem preço",
    "url": null,
    "specifications": {}
  },
  {
    "rank": 33,
    "name": "Todos os artigos",
    "price": "Sem preço",
    "url": "https://www.zoom.com.br/deumzoom",
    "specifications": {}
  },
  {
    "rank": 34,
    "name": "Todos os artigos",
    "price": "Sem preço",
    "url": "https://www.zoom.com.br/deumzoom",
    "specifications": {}
  },
  {
    "rank": 35,
    "name": "Sem título",
    "price": "Sem preço",
    "url": null,
    "specifications": {}
  },
  {
    "rank": 36,
    "name": "Lojas em destaque",
    "price": "Sem preço",
    "url": "https://www.zoom.com.br/cupom-de-desconto/amazon-1582",
    "specifications": {}
  },
  {
    "rank": 37,
    "name": "Lojas em destaque",
    "price": "Sem preço",
    "url": "https://www.zoom.com.br/cupom-de-desconto/amazon-1582",
    "specifications": {}
  },
  {
    "rank": 38,
    "name": "Cashback na Amazon",
    "price": "Sem preço",
    "url": "https://www.zoom.com.br/cupom-de-desconto/amazon-1582",
    "specifications": {}
  },
  {
    "rank": 39,
    "name": "Cashback na Amazon",
    "price": "Sem preço",
    "url": "https://www.zoom.com.br/cupom-de-desconto/amazon-1582",
    "specifications": {}
  },
  {
    "rank": 40,
    "name": "Sem título",
    "price": "Sem preço",
    "url": null,
    "specifications": {}
  },
  {
    "rank": 41,
    "name": "Sem título",
    "price": "Sem preço",
    "url": null,
    "specifications": {}
  },
  {
    "rank": 42,
    "name": "Celulares",
    "price": "Sem preço",
    "url": "https://www.zoom.com.br/celular/iphone",
    "specifications": {}
  },
  {
    "rank": 43,
    "name": "iPhone",
    "price": "Sem preço",
    "url": "https://www.zoom.com.br/celular/iphone",
    "specifications": {}
  },
  {
    "rank": 44,
    "name": "TV 32 polegadas",
    "price": "Sem preço",
    "url": "https://www.zoom.com.br/tv/tamanho-32-polegadas",
    "specifications": {}
  },
  {
    "rank": 45,
    "name": "Lavadora Brastemp",
    "price": "Sem preço",
    "url": "https://www.zoom.com.br/lavadora-roupas/brastemp",
    "specifications": {}
  },
  {
    "rank": 46,
    "name": "Notebook  Samsung",
    "price": "Sem preço",
    "url": "https://www.zoom.com.br/notebook/samsung",
    "specifications": {}
  },
  {
    "rank": 47,
    "name": "Geladeira Electrolux",
    "price": "Sem preço",
    "url": "https://www.zoom.com.br/geladeira/electrolux",
    "specifications": {}
  },
  {
    "rank": 48,
    "name": "Ar-condicionado 7.500 BTUs",
    "price": "Sem preço",
    "url": "https://www.zoom.com.br/ar-condicionado/7-500-btus",
    "specifications": {}
  },
  {
    "rank": 49,
    "name": "Fogão 4 bocas",
    "price": "Sem preço",
    "url": "https://www.zoom.com.br/fogao/4-bocas",
    "specifications": {}
  },
  {
    "rank": 50,
    "name": "Playstation 4",
    "price": "Sem preço",
    "url": "https://www.zoom.com.br/console-de-video-game/playstation-4",
    "specifications": {}
  },
  {
    "rank": 51,
    "name": "Automóveis e Veículos",
    "price": "Sem preço",
    "url": "https://www.zoom.com.br/automoveis-e-veiculos",
    "specifications": {}
  },
  {
    "rank": 52,
    "name": "Cashback na Amazon",
    "price": "Sem preço",
    "url": "https://www.zoom.com.br/cupom-de-desconto/amazon-1582",
    "specifications": {}
  },
  {
    "rank": 53,
    "name": "1ºNotebook Gamer Lenovo LOQ-e 15IAX9E Intel Core i5 12450HX 15,6\" 16GB SSD 512GB Windows 11 83ME0007BR5 (1)Menor preço via Magazine LuizaR$ 4.250,16até 10x de R$ 494,21\n            \n          Frete Grátis 8% de volta na loja todaCompare entre 17 lojas",
    "price": "R$ 4.250,16",
    "url": "https://www.zoom.com.br/notebook/notebook-gamer-lenovo-83me0007br-intel-core-i5-12450h-15-16gb-ssd-512-gb-windows-11-geforce-rtx-3050?_lc=88&searchterm=notebook",
    "specifications": {}
  },
  {
    "rank": 54,
    "name": "1ºNotebook Gamer Lenovo LOQ-e 15IAX9E Intel Core i5 12450HX 15,6\" 16GB SSD 512GB Windows 11 83ME0007BR5 (1)Menor preço via Magazine LuizaR$ 4.250,16até 10x de R$ 494,21\n            \n          Frete Grátis 8% de volta na loja todaCompare entre 17 lojas",
    "price": "R$ 4.250,16",
    "url": "https://www.zoom.com.br/notebook/notebook-gamer-lenovo-83me0007br-intel-core-i5-12450h-15-16gb-ssd-512-gb-windows-11-geforce-rtx-3050?_lc=88&searchterm=notebook",
    "specifications": {}
  },
  {
    "rank": 55,
    "name": "Sem título",
    "price": "Sem preço",
    "url": null,
    "specifications": {}
  },
  {
    "rank": 56,
    "name": "Sem título",
    "price": "Sem preço",
    "url": null,
    "specifications": {}
  },
  {
    "rank": 57,
    "name": "Notebook Gamer Lenovo LOQ-e 15IAX9E Intel Core i5 12450HX 15,6\" 16GB SSD 512GB Windows 11 83ME0007BR",
    "price": "R$ 4.250,16",
    "url": null,
    "specifications": {}
  },
  {
    "rank": 58,
    "name": "Sem título",
    "price": "Sem preço",
    "url": null,
    "specifications": {}
  },
  {
    "rank": 59,
    "name": "Notebook Gamer Lenovo LOQ-e 15IAX9E Intel Core i5 12450HX 15,6\" 16GB SSD 512GB Windows 11 83ME0007BR",
    "price": "R$ 4.250,16",
    "url": null,
    "specifications": {}
  },
  {
    "rank": 60,
    "name": "Notebook Gamer Lenovo LOQ-e 15IAX9E Intel Core i5 12450HX 15,6\" 16GB SSD 512GB Windows 11 83ME0007BR",
    "price": "Sem preço",
    "url": null,
    "specifications": {}
  },
  {
    "rank": 61,
    "name": "Sem título",
    "price": "Sem preço",
    "url": null,
    "specifications": {}
  },
  {
    "rank": 62,
    "name": "Sem título",
    "price": "Sem preço",
    "url": null,
    "specifications": {}
  },
  {
    "rank": 63,
    "name": "2ºIndicaNotebook Lenovo IdeaPad 1i Intel Core i5 1235U 15,6\" 8GB SSD 512GB Windows 11 82VY000QBR4.7 (172)Menor preço via PontoR$ 2.782,00até 12x de R$ 257,59\n            \n          Frete Grátis 0.5% de volta na loja todaCompare entre 16 lojas",
    "price": "R$ 2.782,00",
    "url": "https://www.zoom.com.br/notebook/notebook-lenovo-ideapad-1i-82vy000qbr-intel-core-i5-1235u-15-6-8gb-ssd-512-gb-windows-11?_lc=88&searchterm=notebook",
    "specifications": {}
  },
  {
    "rank": 64,
    "name": "2ºIndicaNotebook Lenovo IdeaPad 1i Intel Core i5 1235U 15,6\" 8GB SSD 512GB Windows 11 82VY000QBR4.7 (172)Menor preço via PontoR$ 2.782,00até 12x de R$ 257,59\n            \n          Frete Grátis 0.5% de volta na loja todaCompare entre 16 lojas",
    "price": "R$ 2.782,00",
    "url": "https://www.zoom.com.br/notebook/notebook-lenovo-ideapad-1i-82vy000qbr-intel-core-i5-1235u-15-6-8gb-ssd-512-gb-windows-11?_lc=88&searchterm=notebook",
    "specifications": {}
  },
  {
    "rank": 65,
    "name": "Sem título",
    "price": "Sem preço",
    "url": null,
    "specifications": {}
  },
  {
    "rank": 66,
    "name": "Sem título",
    "price": "Sem preço",
    "url": null,
    "specifications": {}
  },
  {
    "rank": 67,
    "name": "Notebook Lenovo IdeaPad 1i Intel Core i5 1235U 15,6\" 8GB SSD 512GB Windows 11 82VY000QBR",
    "price": "R$ 2.782,00",
    "url": null,
    "specifications": {}
  },
  {
    "rank": 68,
    "name": "Sem título",
    "price": "Sem preço",
    "url": null,
    "specifications": {}
  },
  {
    "rank": 69,
    "name": "Notebook Lenovo IdeaPad 1i Intel Core i5 1235U 15,6\" 8GB SSD 512GB Windows 11 82VY000QBR",
    "price": "R$ 2.782,00",
    "url": null,
    "specifications": {}
  },
  {
    "rank": 70,
    "name": "Notebook Lenovo IdeaPad 1i Intel Core i5 1235U 15,6\" 8GB SSD 512GB Windows 11 82VY000QBR",
    "price": "Sem preço",
    "url": null,
    "specifications": {}
  },
  {
    "rank": 71,
    "name": "Sem título",
    "price": "Sem preço",
    "url": null,
    "specifications": {}
  },
  {
    "rank": 72,
    "name": "Sem título",
    "price": "Sem preço",
    "url": null,
    "specifications": {}
  },
  {
    "rank": 73,
    "name": "3ºIndicaNotebook Dell Inspiron 15 3520 Intel Core i3 1215U 15,6\" 8GB SSD 512GB Windows 11 i3520wadl1004w4.4 (79)Menor preço via AmazonR$ 2.849,00Compare entre 4 lojas",
    "price": "R$ 2.849,00",
    "url": "https://www.zoom.com.br/notebook/notebook-dell-inspiron-15-3520-i3520wadl1004w-intel-core-i3-1215u-15-6-8gb-ssd-512-gb-windows-11?_lc=88&searchterm=notebook",
    "specifications": {}
  },
  {
    "rank": 74,
    "name": "3ºIndicaNotebook Dell Inspiron 15 3520 Intel Core i3 1215U 15,6\" 8GB SSD 512GB Windows 11 i3520wadl1004w4.4 (79)Menor preço via AmazonR$ 2.849,00Compare entre 4 lojas",
    "price": "R$ 2.849,00",
    "url": "https://www.zoom.com.br/notebook/notebook-dell-inspiron-15-3520-i3520wadl1004w-intel-core-i3-1215u-15-6-8gb-ssd-512-gb-windows-11?_lc=88&searchterm=notebook",
    "specifications": {}
  },
  {
    "rank": 75,
    "name": "Sem título",
    "price": "Sem preço",
    "url": null,
    "specifications": {}
  },
  {
    "rank": 76,
    "name": "Sem título",
    "price": "Sem preço",
    "url": null,
    "specifications": {}
  },
  {
    "rank": 77,
    "name": "Notebook Dell Inspiron 15 3520 Intel Core i3 1215U 15,6\" 8GB SSD 512GB Windows 11 i3520wadl1004w",
    "price": "R$ 2.849,00",
    "url": null,
    "specifications": {}
  },
  {
    "rank": 78,
    "name": "Sem título",
    "price": "Sem preço",
    "url": null,
    "specifications": {}
  },
  {
    "rank": 79,
    "name": "Notebook Dell Inspiron 15 3520 Intel Core i3 1215U 15,6\" 8GB SSD 512GB Windows 11 i3520wadl1004w",
    "price": "R$ 2.849,00",
    "url": null,
    "specifications": {}
  },
  {
    "rank": 80,
    "name": "Notebook Dell Inspiron 15 3520 Intel Core i3 1215U 15,6\" 8GB SSD 512GB Windows 11 i3520wadl1004w",
    "price": "Sem preço",
    "url": null,
    "specifications": {}
  },
  {
    "rank": 81,
    "name": "Sem título",
    "price": "Sem preço",
    "url": null,
    "specifications": {}
  },
  {
    "rank": 82,
    "name": "Sem título",
    "price": "Sem preço",
    "url": null,
    "specifications": {}
  },
  {
    "rank": 83,
    "name": "4ºIndicaNotebook Asus Vivobook Go 15 Intel Celeron Dual Core N4500 15,6\" 4GB SSD 128GB Windows 11 E510KA-BR808WS4.3 (126)Menor preço via ExtraR$ 1.613,70até 10x de R$ 179,30\n            \n           5% de volta na loja todaCompare entre 14 lojas",
    "price": "R$ 1.613,70",
    "url": "https://www.zoom.com.br/notebook/notebook-asus-vivobook-go-e510ka-br808ws-intel-celeron-dual-core-n4500-15-6-4gb-ssd-128-gb-windows-11?_lc=88&searchterm=notebook",
    "specifications": {}
  },
  {
    "rank": 84,
    "name": "4ºIndicaNotebook Asus Vivobook Go 15 Intel Celeron Dual Core N4500 15,6\" 4GB SSD 128GB Windows 11 E510KA-BR808WS4.3 (126)Menor preço via ExtraR$ 1.613,70até 10x de R$ 179,30\n            \n           5% de volta na loja todaCompare entre 14 lojas",
    "price": "R$ 1.613,70",
    "url": "https://www.zoom.com.br/notebook/notebook-asus-vivobook-go-e510ka-br808ws-intel-celeron-dual-core-n4500-15-6-4gb-ssd-128-gb-windows-11?_lc=88&searchterm=notebook",
    "specifications": {}
  },
  {
    "rank": 85,
    "name": "Sem título",
    "price": "Sem preço",
    "url": null,
    "specifications": {}
  },
  {
    "rank": 86,
    "name": "Sem título",
    "price": "Sem preço",
    "url": null,
    "specifications": {}
  },
  {
    "rank": 87,
    "name": "Notebook Asus Vivobook Go 15 Intel Celeron Dual Core N4500 15,6\" 4GB SSD 128GB Windows 11 E510KA-BR808WS",
    "price": "R$ 1.613,70",
    "url": null,
    "specifications": {}
  },
  {
    "rank": 88,
    "name": "Sem título",
    "price": "Sem preço",
    "url": null,
    "specifications": {}
  },
  {
    "rank": 89,
    "name": "Notebook Asus Vivobook Go 15 Intel Celeron Dual Core N4500 15,6\" 4GB SSD 128GB Windows 11 E510KA-BR808WS",
    "price": "R$ 1.613,70",
    "url": null,
    "specifications": {}
  },
  {
    "rank": 90,
    "name": "Notebook Asus Vivobook Go 15 Intel Celeron Dual Core N4500 15,6\" 4GB SSD 128GB Windows 11 E510KA-BR808WS",
    "price": "Sem preço",
    "url": null,
    "specifications": {}
  },
  {
    "rank": 91,
    "name": "Sem título",
    "price": "Sem preço",
    "url": null,
    "specifications": {}
  },
  {
    "rank": 92,
    "name": "Sem título",
    "price": "Sem preço",
    "url": null,
    "specifications": {}
  },
  {
    "rank": 93,
    "name": "5ºIndicaNotebook Acer Aspire 5 Intel Core i5 12450H 8GB RAM 256GB SSD Windows 11 Tela Full HD 15.6 A515-57-55B84.7 (865)Menor preço via AmericanasR$ 2.885,00até 8x de R$ 400,69\n            \n          Compare entre 7 lojas",
    "price": "R$ 2.885,00",
    "url": "https://www.zoom.com.br/notebook/notebook-acer-aspire-5-a515-57-55b8-intel-core-i5-12450h-15-6-8gb-ssd-256-gb-windows-11?_lc=88&searchterm=notebook",
    "specifications": {}
  },
  {
    "rank": 94,
    "name": "5ºIndicaNotebook Acer Aspire 5 Intel Core i5 12450H 8GB RAM 256GB SSD Windows 11 Tela Full HD 15.6 A515-57-55B84.7 (865)Menor preço via AmericanasR$ 2.885,00até 8x de R$ 400,69\n            \n          Compare entre 7 lojas",
    "price": "R$ 2.885,00",
    "url": "https://www.zoom.com.br/notebook/notebook-acer-aspire-5-a515-57-55b8-intel-core-i5-12450h-15-6-8gb-ssd-256-gb-windows-11?_lc=88&searchterm=notebook",
    "specifications": {}
  },
  {
    "rank": 95,
    "name": "Sem título",
    "price": "Sem preço",
    "url": null,
    "specifications": {}
  },
  {
    "rank": 96,
    "name": "Sem título",
    "price": "Sem preço",
    "url": null,
    "specifications": {}
  },
  {
    "rank": 97,
    "name": "Notebook Acer Aspire 5 Intel Core i5 12450H 8GB RAM 256GB SSD Windows 11 Tela Full HD 15.6 A515-57-55B8",
    "price": "R$ 2.885,00",
    "url": null,
    "specifications": {}
  },
  {
    "rank": 98,
    "name": "Sem título",
    "price": "Sem preço",
    "url": null,
    "specifications": {}
  },
  {
    "rank": 99,
    "name": "Notebook Acer Aspire 5 Intel Core i5 12450H 8GB RAM 256GB SSD Windows 11 Tela Full HD 15.6 A515-57-55B8",
    "price": "R$ 2.885,00",
    "url": null,
    "specifications": {}
  },
  {
    "rank": 100,
    "name": "Notebook Acer Aspire 5 Intel Core i5 12450H 8GB RAM 256GB SSD Windows 11 Tela Full HD 15.6 A515-57-55B8",
    "price": "Sem preço",
    "url": null,
    "specifications": {}
  },
  {
    "rank": 101,
    "name": "Sem título",
    "price": "Sem preço",
    "url": null,
    "specifications": {}
  },
  {
    "rank": 102,
    "name": "Sem título",
    "price": "Sem preço",
    "url": null,
    "specifications": {}
  },
  {
    "rank": 103,
    "name": "6ºNotebook Acer Aspire 5 Ryzen 7-5700U 15,6? 12GB SSD 512GB Linux A515-45-R36L4.7 (897)Menor preço via Casas BahiaR$ 3.099,00até 12x de R$ 258,25\n            \n          Frete Grátis 10% de volta na loja todaCompare entre 6 lojas",
    "price": "R$ 3.099,00",
    "url": "https://www.zoom.com.br/notebook/notebook-acer-aspire-5-ryzen-7-5700u-15-6-12gb-ssd-512gb-linux-a515-45-r36l?_lc=88&searchterm=notebook",
    "specifications": {}
  },
  {
    "rank": 104,
    "name": "6ºNotebook Acer Aspire 5 Ryzen 7-5700U 15,6? 12GB SSD 512GB Linux A515-45-R36L4.7 (897)Menor preço via Casas BahiaR$ 3.099,00até 12x de R$ 258,25\n            \n          Frete Grátis 10% de volta na loja todaCompare entre 6 lojas",
    "price": "R$ 3.099,00",
    "url": "https://www.zoom.com.br/notebook/notebook-acer-aspire-5-ryzen-7-5700u-15-6-12gb-ssd-512gb-linux-a515-45-r36l?_lc=88&searchterm=notebook",
    "specifications": {}
  },
  {
    "rank": 105,
    "name": "Sem título",
    "price": "Sem preço",
    "url": null,
    "specifications": {}
  },
  {
    "rank": 106,
    "name": "Sem título",
    "price": "Sem preço",
    "url": null,
    "specifications": {}
  },
  {
    "rank": 107,
    "name": "Notebook Acer Aspire 5 Ryzen 7-5700U 15,6? 12GB SSD 512GB Linux A515-45-R36L",
    "price": "R$ 3.099,00",
    "url": null,
    "specifications": {}
  },
  {
    "rank": 108,
    "name": "Sem título",
    "price": "Sem preço",
    "url": null,
    "specifications": {}
  },
  {
    "rank": 109,
    "name": "Notebook Acer Aspire 5 Ryzen 7-5700U 15,6? 12GB SSD 512GB Linux A515-45-R36L",
    "price": "R$ 3.099,00",
    "url": null,
    "specifications": {}
  },
  {
    "rank": 110,
    "name": "Notebook Acer Aspire 5 Ryzen 7-5700U 15,6? 12GB SSD 512GB Linux A515-45-R36L",
    "price": "Sem preço",
    "url": null,
    "specifications": {}
  },
  {
    "rank": 111,
    "name": "Sem título",
    "price": "Sem preço",
    "url": null,
    "specifications": {}
  },
  {
    "rank": 112,
    "name": "Sem título",
    "price": "Sem preço",
    "url": null,
    "specifications": {}
  },
  {
    "rank": 113,
    "name": "7ºNotebook Lenovo IdeaPad Slim 3i Intel Core i5 13420H 15,3\" 16GB SSD 512GB Windows 11 83NS0001BRMenor preço via Magazine LuizaR$ 3.169,13até 10x de R$ 368,50\n            \n          Frete Grátis 8% de volta na loja todaCompare entre 7 lojas",
    "price": "R$ 3.169,13",
    "url": "https://www.zoom.com.br/notebook/notebook-lenovo-ideapad-83ns0001br-intel-core-i5-13420h-15-16gb-ssd-512-gb-windows-11?_lc=88&searchterm=notebook",
    "specifications": {}
  },
  {
    "rank": 114,
    "name": "7ºNotebook Lenovo IdeaPad Slim 3i Intel Core i5 13420H 15,3\" 16GB SSD 512GB Windows 11 83NS0001BRMenor preço via Magazine LuizaR$ 3.169,13até 10x de R$ 368,50\n            \n          Frete Grátis 8% de volta na loja todaCompare entre 7 lojas",
    "price": "R$ 3.169,13",
    "url": "https://www.zoom.com.br/notebook/notebook-lenovo-ideapad-83ns0001br-intel-core-i5-13420h-15-16gb-ssd-512-gb-windows-11?_lc=88&searchterm=notebook",
    "specifications": {}
  },
  {
    "rank": 115,
    "name": "Sem título",
    "price": "Sem preço",
    "url": null,
    "specifications": {}
  },
  {
    "rank": 116,
    "name": "Sem título",
    "price": "Sem preço",
    "url": null,
    "specifications": {}
  },
  {
    "rank": 117,
    "name": "Notebook Lenovo IdeaPad Slim 3i Intel Core i5 13420H 15,3\" 16GB SSD 512GB Windows 11 83NS0001BR",
    "price": "R$ 3.169,13",
    "url": null,
    "specifications": {}
  },
  {
    "rank": 118,
    "name": "Sem título",
    "price": "Sem preço",
    "url": null,
    "specifications": {}
  },
  {
    "rank": 119,
    "name": "Notebook Lenovo IdeaPad Slim 3i Intel Core i5 13420H 15,3\" 16GB SSD 512GB Windows 11 83NS0001BR",
    "price": "R$ 3.169,13",
    "url": null,
    "specifications": {}
  },
  {
    "rank": 120,
    "name": "Notebook Lenovo IdeaPad Slim 3i Intel Core i5 13420H 15,3\" 16GB SSD 512GB Windows 11 83NS0001BR",
    "price": "Sem preço",
    "url": null,
    "specifications": {}
  },
  {
    "rank": 121,
    "name": "Sem título",
    "price": "Sem preço",
    "url": null,
    "specifications": {}
  },
  {
    "rank": 122,
    "name": "8ºNotebook Samsung Galaxy Book4 Intel Core i5-1335U 15,6\" 16GB SSD 512GB Windows 11 NP750XGJ-KG2BRMenor preço via Magazine LuizaR$ 3.989,05até 10x de R$ 419,90\n            \n          Frete Grátis 8% de volta na loja todaCompare entre 3 lojas",
    "price": "R$ 3.989,05",
    "url": "https://www.zoom.com.br/notebook/notebook-samsung-book-np750xgj-kg2br-intel-core-i5-1335u-15-6-16gb-ssd-512-gb-windows-11?_lc=88&searchterm=notebook",
    "specifications": {}
  },
  {
    "rank": 123,
    "name": "8ºNotebook Samsung Galaxy Book4 Intel Core i5-1335U 15,6\" 16GB SSD 512GB Windows 11 NP750XGJ-KG2BRMenor preço via Magazine LuizaR$ 3.989,05até 10x de R$ 419,90\n            \n          Frete Grátis 8% de volta na loja todaCompare entre 3 lojas",
    "price": "R$ 3.989,05",
    "url": "https://www.zoom.com.br/notebook/notebook-samsung-book-np750xgj-kg2br-intel-core-i5-1335u-15-6-16gb-ssd-512-gb-windows-11?_lc=88&searchterm=notebook",
    "specifications": {}
  },
  {
    "rank": 124,
    "name": "Sem título",
    "price": "Sem preço",
    "url": null,
    "specifications": {}
  },
  {
    "rank": 125,
    "name": "Sem título",
    "price": "Sem preço",
    "url": null,
    "specifications": {}
  },
  {
    "rank": 126,
    "name": "Notebook Samsung Galaxy Book4 Intel Core i5-1335U 15,6\" 16GB SSD 512GB Windows 11 NP750XGJ-KG2BR",
    "price": "R$ 3.989,05",
    "url": null,
    "specifications": {}
  },
  {
    "rank": 127,
    "name": "Sem título",
    "price": "Sem preço",
    "url": null,
    "specifications": {}
  },
  {
    "rank": 128,
    "name": "Notebook Samsung Galaxy Book4 Intel Core i5-1335U 15,6\" 16GB SSD 512GB Windows 11 NP750XGJ-KG2BR",
    "price": "R$ 3.989,05",
    "url": null,
    "specifications": {}
  },
  {
    "rank": 129,
    "name": "Notebook Samsung Galaxy Book4 Intel Core i5-1335U 15,6\" 16GB SSD 512GB Windows 11 NP750XGJ-KG2BR",
    "price": "Sem preço",
    "url": null,
    "specifications": {}
  },
  {
    "rank": 130,
    "name": "Sem título",
    "price": "Sem preço",
    "url": null,
    "specifications": {}
  },
  {
    "rank": 131,
    "name": "9ºIndicaNotebook 2 em 1 Samsung Galaxy Book3 360 NP730QFG-KF2BR Intel Core i5 1335U 13,3\" 8GB SSD 256 GB Windows 11 Caneta Digital Leitor Biométrico Touchscreen4.8 (154)Menor preço via PontoR$ 4.216,89até 10x de R$ 421,69\n            \n           0.5% de volta na loja todaCompare entre 3 lojas",
    "price": "R$ 4.216,89",
    "url": "https://www.zoom.com.br/notebook/notebook-2-em-1-samsung-galaxy-book3-360-np730qfg-kf2br-intel-core-i5-1335u-13-3-8gb-ssd-256-gb-windows-11-caneta-digital-leitor-biometrico-touchscreen?_lc=88&searchterm=notebook",
    "specifications": {}
  },
  {
    "rank": 132,
    "name": "9ºIndicaNotebook 2 em 1 Samsung Galaxy Book3 360 NP730QFG-KF2BR Intel Core i5 1335U 13,3\" 8GB SSD 256 GB Windows 11 Caneta Digital Leitor Biométrico Touchscreen4.8 (154)Menor preço via PontoR$ 4.216,89até 10x de R$ 421,69\n            \n           0.5% de volta na loja todaCompare entre 3 lojas",
    "price": "R$ 4.216,89",
    "url": "https://www.zoom.com.br/notebook/notebook-2-em-1-samsung-galaxy-book3-360-np730qfg-kf2br-intel-core-i5-1335u-13-3-8gb-ssd-256-gb-windows-11-caneta-digital-leitor-biometrico-touchscreen?_lc=88&searchterm=notebook",
    "specifications": {}
  },
  {
    "rank": 133,
    "name": "Sem título",
    "price": "Sem preço",
    "url": null,
    "specifications": {}
  },
  {
    "rank": 134,
    "name": "Sem título",
    "price": "Sem preço",
    "url": null,
    "specifications": {}
  },
  {
    "rank": 135,
    "name": "Notebook 2 em 1 Samsung Galaxy Book3 360 NP730QFG-KF2BR Intel Core i5 1335U 13,3\" 8GB SSD 256 GB Windows 11 Caneta Digital Leitor Biométrico Touchscreen",
    "price": "R$ 4.216,89",
    "url": null,
    "specifications": {}
  },
  {
    "rank": 136,
    "name": "Sem título",
    "price": "Sem preço",
    "url": null,
    "specifications": {}
  },
  {
    "rank": 137,
    "name": "Notebook 2 em 1 Samsung Galaxy Book3 360 NP730QFG-KF2BR Intel Core i5 1335U 13,3\" 8GB SSD 256 GB Windows 11 Caneta Digital Leitor Biométrico Touchscreen",
    "price": "R$ 4.216,89",
    "url": null,
    "specifications": {}
  },
  {
    "rank": 138,
    "name": "Notebook 2 em 1 Samsung Galaxy Book3 360 NP730QFG-KF2BR Intel Core i5 1335U 13,3\" 8GB SSD 256 GB Windows 11 Caneta Digital Leitor Biométrico Touchscreen",
    "price": "Sem preço",
    "url": null,
    "specifications": {}
  },
  {
    "rank": 139,
    "name": "Sem título",
    "price": "Sem preço",
    "url": null,
    "specifications": {}
  },
  {
    "rank": 140,
    "name": "Sem título",
    "price": "Sem preço",
    "url": null,
    "specifications": {}
  },
  {
    "rank": 141,
    "name": "10ºNotebook Asus VivoBook 15 Intel Core i5 1334U 15,6\" 8GB SSD 256GB Windows 11 X1504VA-NJ1737WMenor preço via Fast ShopR$ 2.669,11 0.5% de volta na loja todaCompare entre 9 lojas",
    "price": "R$ 2.669,11",
    "url": "https://www.zoom.com.br/notebook/notebook-asus-vivobook-15-x1504va-nj1737w-intel-core-i5-1334u-15-8gb-ssd-256-gb-windows-11?_lc=88&searchterm=notebook",
    "specifications": {}
  },
  {
    "rank": 142,
    "name": "10ºNotebook Asus VivoBook 15 Intel Core i5 1334U 15,6\" 8GB SSD 256GB Windows 11 X1504VA-NJ1737WMenor preço via Fast ShopR$ 2.669,11 0.5% de volta na loja todaCompare entre 9 lojas",
    "price": "R$ 2.669,11",
    "url": "https://www.zoom.com.br/notebook/notebook-asus-vivobook-15-x1504va-nj1737w-intel-core-i5-1334u-15-8gb-ssd-256-gb-windows-11?_lc=88&searchterm=notebook",
    "specifications": {}
  },
  {
    "rank": 143,
    "name": "Sem título",
    "price": "Sem preço",
    "url": null,
    "specifications": {}
  },
  {
    "rank": 144,
    "name": "Sem título",
    "price": "Sem preço",
    "url": null,
    "specifications": {}
  },
  {
    "rank": 145,
    "name": "Notebook Asus VivoBook 15 Intel Core i5 1334U 15,6\" 8GB SSD 256GB Windows 11 X1504VA-NJ1737W",
    "price": "R$ 2.669,11",
    "url": null,
    "specifications": {}
  },
  {
    "rank": 146,
    "name": "Sem título",
    "price": "Sem preço",
    "url": null,
    "specifications": {}
  },
  {
    "rank": 147,
    "name": "Notebook Asus VivoBook 15 Intel Core i5 1334U 15,6\" 8GB SSD 256GB Windows 11 X1504VA-NJ1737W",
    "price": "R$ 2.669,11",
    "url": null,
    "specifications": {}
  },
  {
    "rank": 148,
    "name": "Notebook Asus VivoBook 15 Intel Core i5 1334U 15,6\" 8GB SSD 256GB Windows 11 X1504VA-NJ1737W",
    "price": "Sem preço",
    "url": null,
    "specifications": {}
  },
  {
    "rank": 149,
    "name": "Sem título",
    "price": "Sem preço",
    "url": null,
    "specifications": {}
  },
  {
    "rank": 150,
    "name": "Notebook Dell Inspiron 15 3530 Intel i5 1335U 15,6\" 16GB SSD 512GB Windows 11 brpichbto3530gqpbw4.8 (9)Menor preço via Magazine LuizaR$ 3.782,03até 10x de R$ 389,90\n            \n          Frete Grátis 8% de volta na loja todaCompare entre 5 lojas",
    "price": "R$ 3.782,03",
    "url": "https://www.zoom.com.br/notebook/notebook-dell-inspiron-brpichbto3530gqpbw-intel-core-i5-1335u-15-6-16gb-ssd-512-gb-windows-11?_lc=88&searchterm=notebook",
    "specifications": {}
  },
  {
    "rank": 151,
    "name": "Notebook Dell Inspiron 15 3530 Intel i5 1335U 15,6\" 16GB SSD 512GB Windows 11 brpichbto3530gqpbw4.8 (9)Menor preço via Magazine LuizaR$ 3.782,03até 10x de R$ 389,90\n            \n          Frete Grátis 8% de volta na loja todaCompare entre 5 lojas",
    "price": "R$ 3.782,03",
    "url": "https://www.zoom.com.br/notebook/notebook-dell-inspiron-brpichbto3530gqpbw-intel-core-i5-1335u-15-6-16gb-ssd-512-gb-windows-11?_lc=88&searchterm=notebook",
    "specifications": {}
  },
  {
    "rank": 152,
    "name": "Sem título",
    "price": "Sem preço",
    "url": null,
    "specifications": {}
  },
  {
    "rank": 153,
    "name": "Sem título",
    "price": "Sem preço",
    "url": null,
    "specifications": {}
  },
  {
    "rank": 154,
    "name": "Notebook Dell Inspiron 15 3530 Intel i5 1335U 15,6\" 16GB SSD 512GB Windows 11 brpichbto3530gqpbw",
    "price": "R$ 3.782,03",
    "url": null,
    "specifications": {}
  },
  {
    "rank": 155,
    "name": "Sem título",
    "price": "Sem preço",
    "url": null,
    "specifications": {}
  },
  {
    "rank": 156,
    "name": "Notebook Dell Inspiron 15 3530 Intel i5 1335U 15,6\" 16GB SSD 512GB Windows 11 brpichbto3530gqpbw",
    "price": "R$ 3.782,03",
    "url": null,
    "specifications": {}
  },
  {
    "rank": 157,
    "name": "Notebook Dell Inspiron 15 3530 Intel i5 1335U 15,6\" 16GB SSD 512GB Windows 11 brpichbto3530gqpbw",
    "price": "Sem preço",
    "url": null,
    "specifications": {}
  },
  {
    "rank": 158,
    "name": "Sem título",
    "price": "Sem preço",
    "url": null,
    "specifications": {}
  },
  {
    "rank": 159,
    "name": "Sem título",
    "price": "Sem preço",
    "url": null,
    "specifications": {}
  },
  {
    "rank": 160,
    "name": "IndicaNotebook Acer Aspire 3 A315-510P-34XC Intel Core i3 N305 15,6\" 8GB SSD 256 GB Windows 114.7 (237)Menor preço via Casas BahiaR$ 2.458,00até 12x de R$ 227,59\n            \n          Frete Grátis 10% de volta na loja todaCompare entre 15 lojas",
    "price": "R$ 2.458,00",
    "url": "https://www.zoom.com.br/notebook/notebook-acer-aspire-3-a315-510p-34xc-intel-core-i3-n305-15-6-8gb-ssd-256-gb-windows-11?_lc=88&searchterm=notebook",
    "specifications": {}
  },
  {
    "rank": 161,
    "name": "IndicaNotebook Acer Aspire 3 A315-510P-34XC Intel Core i3 N305 15,6\" 8GB SSD 256 GB Windows 114.7 (237)Menor preço via Casas BahiaR$ 2.458,00até 12x de R$ 227,59\n            \n          Frete Grátis 10% de volta na loja todaCompare entre 15 lojas",
    "price": "R$ 2.458,00",
    "url": "https://www.zoom.com.br/notebook/notebook-acer-aspire-3-a315-510p-34xc-intel-core-i3-n305-15-6-8gb-ssd-256-gb-windows-11?_lc=88&searchterm=notebook",
    "specifications": {}
  },
  {
    "rank": 162,
    "name": "Sem título",
    "price": "Sem preço",
    "url": null,
    "specifications": {}
  },
  {
    "rank": 163,
    "name": "Sem título",
    "price": "Sem preço",
    "url": null,
    "specifications": {}
  },
  {
    "rank": 164,
    "name": "Notebook Acer Aspire 3 A315-510P-34XC Intel Core i3 N305 15,6\" 8GB SSD 256 GB Windows 11",
    "price": "R$ 2.458,00",
    "url": null,
    "specifications": {}
  },
  {
    "rank": 165,
    "name": "Sem título",
    "price": "Sem preço",
    "url": null,
    "specifications": {}
  },
  {
    "rank": 166,
    "name": "Notebook Acer Aspire 3 A315-510P-34XC Intel Core i3 N305 15,6\" 8GB SSD 256 GB Windows 11",
    "price": "R$ 2.458,00",
    "url": null,
    "specifications": {}
  },
  {
    "rank": 167,
    "name": "Notebook Acer Aspire 3 A315-510P-34XC Intel Core i3 N305 15,6\" 8GB SSD 256 GB Windows 11",
    "price": "Sem preço",
    "url": null,
    "specifications": {}
  },
  {
    "rank": 168,
    "name": "Sem título",
    "price": "Sem preço",
    "url": null,
    "specifications": {}
  },
  {
    "rank": 169,
    "name": "Sem título",
    "price": "Sem preço",
    "url": null,
    "specifications": {}
  },
  {
    "rank": 170,
    "name": "Notebook Gamer Acer Nitro V 15 Intel Core i5 13420H RTX 3050 15,6\" 8GB SSD 512GB Linux ANV15-51-57WS4 (10)Menor preço via Fast ShopR$ 4.404,28 0.5% de volta na loja todaCompare entre 6 lojas",
    "price": "R$ 4.404,28",
    "url": "https://www.zoom.com.br/notebook/notebook-gamer-acer-nitro-v-anv15-51-57ws-intel-core-i5-13420h-15-6-8gb-ssd-512-gb-linux-geforce-rtx-3050?_lc=88&searchterm=notebook",
    "specifications": {}
  },
  {
    "rank": 171,
    "name": "Notebook Gamer Acer Nitro V 15 Intel Core i5 13420H RTX 3050 15,6\" 8GB SSD 512GB Linux ANV15-51-57WS4 (10)Menor preço via Fast ShopR$ 4.404,28 0.5% de volta na loja todaCompare entre 6 lojas",
    "price": "R$ 4.404,28",
    "url": "https://www.zoom.com.br/notebook/notebook-gamer-acer-nitro-v-anv15-51-57ws-intel-core-i5-13420h-15-6-8gb-ssd-512-gb-linux-geforce-rtx-3050?_lc=88&searchterm=notebook",
    "specifications": {}
  },
  {
    "rank": 172,
    "name": "Sem título",
    "price": "Sem preço",
    "url": null,
    "specifications": {}
  },
  {
    "rank": 173,
    "name": "Sem título",
    "price": "Sem preço",
    "url": null,
    "specifications": {}
  },
  {
    "rank": 174,
    "name": "Notebook Gamer Acer Nitro V 15 Intel Core i5 13420H RTX 3050 15,6\" 8GB SSD 512GB Linux ANV15-51-57WS",
    "price": "R$ 4.404,28",
    "url": null,
    "specifications": {}
  },
  {
    "rank": 175,
    "name": "Sem título",
    "price": "Sem preço",
    "url": null,
    "specifications": {}
  },
  {
    "rank": 176,
    "name": "Notebook Gamer Acer Nitro V 15 Intel Core i5 13420H RTX 3050 15,6\" 8GB SSD 512GB Linux ANV15-51-57WS",
    "price": "R$ 4.404,28",
    "url": null,
    "specifications": {}
  },
  {
    "rank": 177,
    "name": "Notebook Gamer Acer Nitro V 15 Intel Core i5 13420H RTX 3050 15,6\" 8GB SSD 512GB Linux ANV15-51-57WS",
    "price": "Sem preço",
    "url": null,
    "specifications": {}
  },
  {
    "rank": 178,
    "name": "Sem título",
    "price": "Sem preço",
    "url": null,
    "specifications": {}
  },
  {
    "rank": 179,
    "name": "Sem título",
    "price": "Sem preço",
    "url": null,
    "specifications": {}
  },
  {
    "rank": 180,
    "name": "Notebook Lenovo IdeaPad 1 AMD Ryzen 5 7520U 15,6\" 8GB SSD 512GB Windows 11 82X5000GBR4.9 (22)Menor preço via Magazine LuizaR$ 2.321,14até 10x de R$ 269,90\n            \n          Frete Grátis 8% de volta na loja todaCompare entre 7 lojas",
    "price": "R$ 2.321,14",
    "url": "https://www.zoom.com.br/notebook/notebook-lenovo-ideapad-1-82x5000gbr-amd-ryzen-5-7520u-15-6-8gb-ssd-512-gb-windows-11?_lc=88&searchterm=notebook",
    "specifications": {}
  },
  {
    "rank": 181,
    "name": "Notebook Lenovo IdeaPad 1 AMD Ryzen 5 7520U 15,6\" 8GB SSD 512GB Windows 11 82X5000GBR4.9 (22)Menor preço via Magazine LuizaR$ 2.321,14até 10x de R$ 269,90\n            \n          Frete Grátis 8% de volta na loja todaCompare entre 7 lojas",
    "price": "R$ 2.321,14",
    "url": "https://www.zoom.com.br/notebook/notebook-lenovo-ideapad-1-82x5000gbr-amd-ryzen-5-7520u-15-6-8gb-ssd-512-gb-windows-11?_lc=88&searchterm=notebook",
    "specifications": {}
  },
  {
    "rank": 182,
    "name": "Sem título",
    "price": "Sem preço",
    "url": null,
    "specifications": {}
  },
  {
    "rank": 183,
    "name": "Sem título",
    "price": "Sem preço",
    "url": null,
    "specifications": {}
  },
  {
    "rank": 184,
    "name": "Notebook Lenovo IdeaPad 1 AMD Ryzen 5 7520U 15,6\" 8GB SSD 512GB Windows 11 82X5000GBR",
    "price": "R$ 2.321,14",
    "url": null,
    "specifications": {}
  },
  {
    "rank": 185,
    "name": "Sem título",
    "price": "Sem preço",
    "url": null,
    "specifications": {}
  },
  {
    "rank": 186,
    "name": "Notebook Lenovo IdeaPad 1 AMD Ryzen 5 7520U 15,6\" 8GB SSD 512GB Windows 11 82X5000GBR",
    "price": "R$ 2.321,14",
    "url": null,
    "specifications": {}
  },
  {
    "rank": 187,
    "name": "Notebook Lenovo IdeaPad 1 AMD Ryzen 5 7520U 15,6\" 8GB SSD 512GB Windows 11 82X5000GBR",
    "price": "Sem preço",
    "url": null,
    "specifications": {}
  },
  {
    "rank": 188,
    "name": "Sem título",
    "price": "Sem preço",
    "url": null,
    "specifications": {}
  },
  {
    "rank": 189,
    "name": "Sem título",
    "price": "Sem preço",
    "url": null,
    "specifications": {}
  },
  {
    "rank": 190,
    "name": "Notebook Dell Inspiron 15 3520 Intel Core i5 1235U 15,6\" 16GB SSD 512GB Windows 11 i3520wadl1012w4.4 (68)Menor preço via ExtraR$ 3.365,10até 10x de R$ 373,90\n            \n          Frete Grátis 5% de volta na loja todaCompare entre 3 lojas",
    "price": "R$ 3.365,10",
    "url": "https://www.zoom.com.br/notebook/notebook-dell-inspiron-15-3520-i3520uadl1012w-intel-core-i5-1235u-15-6-16gb-ssd-512-gb-windows-11-leitor-biometrico?_lc=88&searchterm=notebook",
    "specifications": {}
  },
  {
    "rank": 191,
    "name": "Notebook Dell Inspiron 15 3520 Intel Core i5 1235U 15,6\" 16GB SSD 512GB Windows 11 i3520wadl1012w4.4 (68)Menor preço via ExtraR$ 3.365,10até 10x de R$ 373,90\n            \n          Frete Grátis 5% de volta na loja todaCompare entre 3 lojas",
    "price": "R$ 3.365,10",
    "url": "https://www.zoom.com.br/notebook/notebook-dell-inspiron-15-3520-i3520uadl1012w-intel-core-i5-1235u-15-6-16gb-ssd-512-gb-windows-11-leitor-biometrico?_lc=88&searchterm=notebook",
    "specifications": {}
  },
  {
    "rank": 192,
    "name": "Sem título",
    "price": "Sem preço",
    "url": null,
    "specifications": {}
  },
  {
    "rank": 193,
    "name": "Sem título",
    "price": "Sem preço",
    "url": null,
    "specifications": {}
  },
  {
    "rank": 194,
    "name": "Notebook Dell Inspiron 15 3520 Intel Core i5 1235U 15,6\" 16GB SSD 512GB Windows 11 i3520wadl1012w",
    "price": "R$ 3.365,10",
    "url": null,
    "specifications": {}
  },
  {
    "rank": 195,
    "name": "Sem título",
    "price": "Sem preço",
    "url": null,
    "specifications": {}
  },
  {
    "rank": 196,
    "name": "Notebook Dell Inspiron 15 3520 Intel Core i5 1235U 15,6\" 16GB SSD 512GB Windows 11 i3520wadl1012w",
    "price": "R$ 3.365,10",
    "url": null,
    "specifications": {}
  },
  {
    "rank": 197,
    "name": "Notebook Dell Inspiron 15 3520 Intel Core i5 1235U 15,6\" 16GB SSD 512GB Windows 11 i3520wadl1012w",
    "price": "Sem preço",
    "url": null,
    "specifications": {}
  },
  {
    "rank": 198,
    "name": "Sem título",
    "price": "Sem preço",
    "url": null,
    "specifications": {}
  },
  {
    "rank": 199,
    "name": "Sem título",
    "price": "Sem preço",
    "url": null,
    "specifications": {}
  },
  {
    "rank": 200,
    "name": "Notebook Dell Inspiron 15 Intel Core i5 1235U 15,6\" 16GB SSD 1TB Windows 11 I15-I120K-A35PMenor preço via Magazine LuizaR$ 3.959,10até 10x de R$ 439,90\n            \n          Frete Grátis 8% de volta na loja todaCompare entre 4 lojas",
    "price": "R$ 3.959,10",
    "url": "https://www.zoom.com.br/notebook/notebook-dell-inspiron-15-i15-i120k-a35p-intel-core-i5-1235u-15-6-16gb-ssd-1-tb-windows-11?_lc=88&searchterm=notebook",
    "specifications": {}
  },
  {
    "rank": 201,
    "name": "Notebook Dell Inspiron 15 Intel Core i5 1235U 15,6\" 16GB SSD 1TB Windows 11 I15-I120K-A35PMenor preço via Magazine LuizaR$ 3.959,10até 10x de R$ 439,90\n            \n          Frete Grátis 8% de volta na loja todaCompare entre 4 lojas",
    "price": "R$ 3.959,10",
    "url": "https://www.zoom.com.br/notebook/notebook-dell-inspiron-15-i15-i120k-a35p-intel-core-i5-1235u-15-6-16gb-ssd-1-tb-windows-11?_lc=88&searchterm=notebook",
    "specifications": {}
  },
  {
    "rank": 202,
    "name": "Sem título",
    "price": "Sem preço",
    "url": null,
    "specifications": {}
  },
  {
    "rank": 203,
    "name": "Sem título",
    "price": "Sem preço",
    "url": null,
    "specifications": {}
  },
  {
    "rank": 204,
    "name": "Notebook Dell Inspiron 15 Intel Core i5 1235U 15,6\" 16GB SSD 1TB Windows 11 I15-I120K-A35P",
    "price": "R$ 3.959,10",
    "url": null,
    "specifications": {}
  },
  {
    "rank": 205,
    "name": "Sem título",
    "price": "Sem preço",
    "url": null,
    "specifications": {}
  },
  {
    "rank": 206,
    "name": "Notebook Dell Inspiron 15 Intel Core i5 1235U 15,6\" 16GB SSD 1TB Windows 11 I15-I120K-A35P",
    "price": "R$ 3.959,10",
    "url": null,
    "specifications": {}
  },
  {
    "rank": 207,
    "name": "Notebook Dell Inspiron 15 Intel Core i5 1235U 15,6\" 16GB SSD 1TB Windows 11 I15-I120K-A35P",
    "price": "Sem preço",
    "url": null,
    "specifications": {}
  },
  {
    "rank": 208,
    "name": "Sem título",
    "price": "Sem preço",
    "url": null,
    "specifications": {}
  },
  {
    "rank": 209,
    "name": "Notebook Gamer Acer Nitro V Intel Core i7-13620H RTX 4050 15,6' 16GB SSD 512GB Linux ANV15-51-7037 Menor preço via Casas BahiaR$ 6.349,00até 12x de R$ 529,08\n            \n          Frete Grátis 10% de volta na loja todaCompare entre 4 lojas",
    "price": "R$ 6.349,00",
    "url": "https://www.zoom.com.br/notebook/notebook-gamer-acer-nitro-v-anv15-51-7037-intel-core-i7-13620h-15-6-16gb-ssd-512-gb-linux-geforce-rtx-4050?_lc=88&searchterm=notebook",
    "specifications": {}
  },
  {
    "rank": 210,
    "name": "Notebook Gamer Acer Nitro V Intel Core i7-13620H RTX 4050 15,6' 16GB SSD 512GB Linux ANV15-51-7037 Menor preço via Casas BahiaR$ 6.349,00até 12x de R$ 529,08\n            \n          Frete Grátis 10% de volta na loja todaCompare entre 4 lojas",
    "price": "R$ 6.349,00",
    "url": "https://www.zoom.com.br/notebook/notebook-gamer-acer-nitro-v-anv15-51-7037-intel-core-i7-13620h-15-6-16gb-ssd-512-gb-linux-geforce-rtx-4050?_lc=88&searchterm=notebook",
    "specifications": {}
  },
  {
    "rank": 211,
    "name": "Sem título",
    "price": "Sem preço",
    "url": null,
    "specifications": {}
  },
  {
    "rank": 212,
    "name": "Sem título",
    "price": "Sem preço",
    "url": null,
    "specifications": {}
  },
  {
    "rank": 213,
    "name": "Notebook Gamer Acer Nitro V Intel Core i7-13620H RTX 4050 15,6' 16GB SSD 512GB Linux ANV15-51-7037",
    "price": "R$ 6.349,00",
    "url": null,
    "specifications": {}
  },
  {
    "rank": 214,
    "name": "Sem título",
    "price": "Sem preço",
    "url": null,
    "specifications": {}
  },
  {
    "rank": 215,
    "name": "Notebook Gamer Acer Nitro V Intel Core i7-13620H RTX 4050 15,6' 16GB SSD 512GB Linux ANV15-51-7037",
    "price": "R$ 6.349,00",
    "url": null,
    "specifications": {}
  },
  {
    "rank": 216,
    "name": "Notebook Gamer Acer Nitro V Intel Core i7-13620H RTX 4050 15,6' 16GB SSD 512GB Linux ANV15-51-7037",
    "price": "Sem preço",
    "url": null,
    "specifications": {}
  },
  {
    "rank": 217,
    "name": "Sem título",
    "price": "Sem preço",
    "url": null,
    "specifications": {}
  },
  {
    "rank": 218,
    "name": "IndicaNotebook Gamer Acer Nitro V 15 Intel Core i5 13420H RTX 3050 15,6\" 8GB SSD 512GB Windows 11 ANV15-51-58AZ4.7 (390)Menor preço via AmazonR$ 4.826,00Compare entre 11 lojas",
    "price": "R$ 4.826,00",
    "url": "https://www.zoom.com.br/notebook/notebook-gamer-acer-nitro-v-anv15-51-58az-intel-core-i5-13420h-15-6-8gb-ssd-512-gb-windows-11-geforce-rtx-3050?_lc=88&searchterm=notebook",
    "specifications": {}
  },
  {
    "rank": 219,
    "name": "IndicaNotebook Gamer Acer Nitro V 15 Intel Core i5 13420H RTX 3050 15,6\" 8GB SSD 512GB Windows 11 ANV15-51-58AZ4.7 (390)Menor preço via AmazonR$ 4.826,00Compare entre 11 lojas",
    "price": "R$ 4.826,00",
    "url": "https://www.zoom.com.br/notebook/notebook-gamer-acer-nitro-v-anv15-51-58az-intel-core-i5-13420h-15-6-8gb-ssd-512-gb-windows-11-geforce-rtx-3050?_lc=88&searchterm=notebook",
    "specifications": {}
  },
  {
    "rank": 220,
    "name": "Sem título",
    "price": "Sem preço",
    "url": null,
    "specifications": {}
  },
  {
    "rank": 221,
    "name": "Sem título",
    "price": "Sem preço",
    "url": null,
    "specifications": {}
  },
  {
    "rank": 222,
    "name": "Notebook Gamer Acer Nitro V 15 Intel Core i5 13420H RTX 3050 15,6\" 8GB SSD 512GB Windows 11 ANV15-51-58AZ",
    "price": "R$ 4.826,00",
    "url": null,
    "specifications": {}
  },
  {
    "rank": 223,
    "name": "Sem título",
    "price": "Sem preço",
    "url": null,
    "specifications": {}
  },
  {
    "rank": 224,
    "name": "Notebook Gamer Acer Nitro V 15 Intel Core i5 13420H RTX 3050 15,6\" 8GB SSD 512GB Windows 11 ANV15-51-58AZ",
    "price": "R$ 4.826,00",
    "url": null,
    "specifications": {}
  },
  {
    "rank": 225,
    "name": "Notebook Gamer Acer Nitro V 15 Intel Core i5 13420H RTX 3050 15,6\" 8GB SSD 512GB Windows 11 ANV15-51-58AZ",
    "price": "Sem preço",
    "url": null,
    "specifications": {}
  },
  {
    "rank": 226,
    "name": "Sem título",
    "price": "Sem preço",
    "url": null,
    "specifications": {}
  },
  {
    "rank": 227,
    "name": "Sem título",
    "price": "Sem preço",
    "url": null,
    "specifications": {}
  },
  {
    "rank": 228,
    "name": "Notebook Samsung Galaxy Book4 Intel Core i5-1335U 15,6\" 8GB SSD 256GB Windows 11 NP750XGJ-KG4BRMenor preço via ExtraR$ 3.419,33até 10x de R$ 341,93\n            \n          Frete Grátis 5% de volta na loja todaCompare entre 6 lojas",
    "price": "R$ 3.419,33",
    "url": "https://www.zoom.com.br/notebook/notebook-samsung-book-np750xgj-kg4br-intel-core-i5-1335u-15-6-8gb-ssd-256-gb-windows-11?_lc=88&searchterm=notebook",
    "specifications": {}
  },
  {
    "rank": 229,
    "name": "Notebook Samsung Galaxy Book4 Intel Core i5-1335U 15,6\" 8GB SSD 256GB Windows 11 NP750XGJ-KG4BRMenor preço via ExtraR$ 3.419,33até 10x de R$ 341,93\n            \n          Frete Grátis 5% de volta na loja todaCompare entre 6 lojas",
    "price": "R$ 3.419,33",
    "url": "https://www.zoom.com.br/notebook/notebook-samsung-book-np750xgj-kg4br-intel-core-i5-1335u-15-6-8gb-ssd-256-gb-windows-11?_lc=88&searchterm=notebook",
    "specifications": {}
  },
  {
    "rank": 230,
    "name": "Sem título",
    "price": "Sem preço",
    "url": null,
    "specifications": {}
  },
  {
    "rank": 231,
    "name": "Sem título",
    "price": "Sem preço",
    "url": null,
    "specifications": {}
  },
  {
    "rank": 232,
    "name": "Notebook Samsung Galaxy Book4 Intel Core i5-1335U 15,6\" 8GB SSD 256GB Windows 11 NP750XGJ-KG4BR",
    "price": "R$ 3.419,33",
    "url": null,
    "specifications": {}
  },
  {
    "rank": 233,
    "name": "Sem título",
    "price": "Sem preço",
    "url": null,
    "specifications": {}
  },
  {
    "rank": 234,
    "name": "Notebook Samsung Galaxy Book4 Intel Core i5-1335U 15,6\" 8GB SSD 256GB Windows 11 NP750XGJ-KG4BR",
    "price": "R$ 3.419,33",
    "url": null,
    "specifications": {}
  },
  {
    "rank": 235,
    "name": "Notebook Samsung Galaxy Book4 Intel Core i5-1335U 15,6\" 8GB SSD 256GB Windows 11 NP750XGJ-KG4BR",
    "price": "Sem preço",
    "url": null,
    "specifications": {}
  },
  {
    "rank": 236,
    "name": "Sem título",
    "price": "Sem preço",
    "url": null,
    "specifications": {}
  },
  {
    "rank": 237,
    "name": "Notebook Gamer Dell G15 5530 Intel Core i5 13450HX RTX 3050 15,6\" 8GB SSD 256GB Windows 11 G15-i1300-M10Menor preço via Casas BahiaR$ 4.499,10até 12x de R$ 416,58\n            \n           10% de volta na loja todaCompare entre 2 lojas",
    "price": "R$ 4.499,10",
    "url": "https://www.zoom.com.br/notebook/notebook-gamer-dell-g-series-g15-5530-g15-i1300-m10-intel-core-i5-13450hx-15-6-8gb-ssd-256-gb-windows-11-geforce-rtx-3050?_lc=88&searchterm=notebook",
    "specifications": {}
  },
  {
    "rank": 238,
    "name": "Notebook Gamer Dell G15 5530 Intel Core i5 13450HX RTX 3050 15,6\" 8GB SSD 256GB Windows 11 G15-i1300-M10Menor preço via Casas BahiaR$ 4.499,10até 12x de R$ 416,58\n            \n           10% de volta na loja todaCompare entre 2 lojas",
    "price": "R$ 4.499,10",
    "url": "https://www.zoom.com.br/notebook/notebook-gamer-dell-g-series-g15-5530-g15-i1300-m10-intel-core-i5-13450hx-15-6-8gb-ssd-256-gb-windows-11-geforce-rtx-3050?_lc=88&searchterm=notebook",
    "specifications": {}
  },
  {
    "rank": 239,
    "name": "Sem título",
    "price": "Sem preço",
    "url": null,
    "specifications": {}
  },
  {
    "rank": 240,
    "name": "Sem título",
    "price": "Sem preço",
    "url": null,
    "specifications": {}
  },
  {
    "rank": 241,
    "name": "Notebook Gamer Dell G15 5530 Intel Core i5 13450HX RTX 3050 15,6\" 8GB SSD 256GB Windows 11 G15-i1300-M10",
    "price": "R$ 4.499,10",
    "url": null,
    "specifications": {}
  },
  {
    "rank": 242,
    "name": "Sem título",
    "price": "Sem preço",
    "url": null,
    "specifications": {}
  },
  {
    "rank": 243,
    "name": "Notebook Gamer Dell G15 5530 Intel Core i5 13450HX RTX 3050 15,6\" 8GB SSD 256GB Windows 11 G15-i1300-M10",
    "price": "R$ 4.499,10",
    "url": null,
    "specifications": {}
  },
  {
    "rank": 244,
    "name": "Notebook Gamer Dell G15 5530 Intel Core i5 13450HX RTX 3050 15,6\" 8GB SSD 256GB Windows 11 G15-i1300-M10",
    "price": "Sem preço",
    "url": null,
    "specifications": {}
  },
  {
    "rank": 245,
    "name": "Sem título",
    "price": "Sem preço",
    "url": null,
    "specifications": {}
  },
  {
    "rank": 246,
    "name": "Notebook Lenovo IdeaPad Slim 3i Intel Core i5 13420H 15,3\" 8GB SSD 512GB Linux 83NSS00000Menor preço via Magazine LuizaR$ 2.668,61até 10x de R$ 310,30\n            \n          Frete Grátis 8% de volta na loja todaCompare entre 8 lojas",
    "price": "R$ 2.668,61",
    "url": "https://www.zoom.com.br/notebook/notebook-lenovo-ideapad-83nss00000-intel-core-i5-13420h-15-8gb-ssd-512-gb-linux?_lc=88&searchterm=notebook",
    "specifications": {}
  },
  {
    "rank": 247,
    "name": "Notebook Lenovo IdeaPad Slim 3i Intel Core i5 13420H 15,3\" 8GB SSD 512GB Linux 83NSS00000Menor preço via Magazine LuizaR$ 2.668,61até 10x de R$ 310,30\n            \n          Frete Grátis 8% de volta na loja todaCompare entre 8 lojas",
    "price": "R$ 2.668,61",
    "url": "https://www.zoom.com.br/notebook/notebook-lenovo-ideapad-83nss00000-intel-core-i5-13420h-15-8gb-ssd-512-gb-linux?_lc=88&searchterm=notebook",
    "specifications": {}
  },
  {
    "rank": 248,
    "name": "Sem título",
    "price": "Sem preço",
    "url": null,
    "specifications": {}
  },
  {
    "rank": 249,
    "name": "Sem título",
    "price": "Sem preço",
    "url": null,
    "specifications": {}
  },
  {
    "rank": 250,
    "name": "Notebook Lenovo IdeaPad Slim 3i Intel Core i5 13420H 15,3\" 8GB SSD 512GB Linux 83NSS00000",
    "price": "R$ 2.668,61",
    "url": null,
    "specifications": {}
  },
  {
    "rank": 251,
    "name": "Sem título",
    "price": "Sem preço",
    "url": null,
    "specifications": {}
  },
  {
    "rank": 252,
    "name": "Notebook Lenovo IdeaPad Slim 3i Intel Core i5 13420H 15,3\" 8GB SSD 512GB Linux 83NSS00000",
    "price": "R$ 2.668,61",
    "url": null,
    "specifications": {}
  },
  {
    "rank": 253,
    "name": "Notebook Lenovo IdeaPad Slim 3i Intel Core i5 13420H 15,3\" 8GB SSD 512GB Linux 83NSS00000",
    "price": "Sem preço",
    "url": null,
    "specifications": {}
  },
  {
    "rank": 254,
    "name": "Sem título",
    "price": "Sem preço",
    "url": null,
    "specifications": {}
  },
  {
    "rank": 255,
    "name": "IndicaNotebook Samsung Galaxy Book4 Intel Core i5 1335U 15,6\" 8GB SSD 512GB Windows 11 NP750XGJ-KG3BR4.7 (259)Menor preço via Magazine LuizaR$ 3.827,55até 10x de R$ 402,90\n            \n          Frete Grátis 8% de volta na loja todaCompare entre 5 lojas",
    "price": "R$ 3.827,55",
    "url": "https://www.zoom.com.br/notebook/notebook-samsung-book-np750xgj-kg3br-intel-core-i5-1335u-15-6-8gb-ssd-512-gb-windows-11?_lc=88&searchterm=notebook",
    "specifications": {}
  },
  {
    "rank": 256,
    "name": "IndicaNotebook Samsung Galaxy Book4 Intel Core i5 1335U 15,6\" 8GB SSD 512GB Windows 11 NP750XGJ-KG3BR4.7 (259)Menor preço via Magazine LuizaR$ 3.827,55até 10x de R$ 402,90\n            \n          Frete Grátis 8% de volta na loja todaCompare entre 5 lojas",
    "price": "R$ 3.827,55",
    "url": "https://www.zoom.com.br/notebook/notebook-samsung-book-np750xgj-kg3br-intel-core-i5-1335u-15-6-8gb-ssd-512-gb-windows-11?_lc=88&searchterm=notebook",
    "specifications": {}
  },
  {
    "rank": 257,
    "name": "Sem título",
    "price": "Sem preço",
    "url": null,
    "specifications": {}
  },
  {
    "rank": 258,
    "name": "Sem título",
    "price": "Sem preço",
    "url": null,
    "specifications": {}
  },
  {
    "rank": 259,
    "name": "Notebook Samsung Galaxy Book4 Intel Core i5 1335U 15,6\" 8GB SSD 512GB Windows 11 NP750XGJ-KG3BR",
    "price": "R$ 3.827,55",
    "url": null,
    "specifications": {}
  },
  {
    "rank": 260,
    "name": "Sem título",
    "price": "Sem preço",
    "url": null,
    "specifications": {}
  },
  {
    "rank": 261,
    "name": "Notebook Samsung Galaxy Book4 Intel Core i5 1335U 15,6\" 8GB SSD 512GB Windows 11 NP750XGJ-KG3BR",
    "price": "R$ 3.827,55",
    "url": null,
    "specifications": {}
  },
  {
    "rank": 262,
    "name": "Notebook Samsung Galaxy Book4 Intel Core i5 1335U 15,6\" 8GB SSD 512GB Windows 11 NP750XGJ-KG3BR",
    "price": "Sem preço",
    "url": null,
    "specifications": {}
  },
  {
    "rank": 263,
    "name": "Sem título",
    "price": "Sem preço",
    "url": null,
    "specifications": {}
  },
  {
    "rank": 264,
    "name": "Sem título",
    "price": "Sem preço",
    "url": null,
    "specifications": {}
  },
  {
    "rank": 265,
    "name": "Notebook Lenovo Ideapad 1 AMD Ryzen 3-7320U 15,6\" 8GB SSD 256GB Windows 11 82X5000ABR4.6 (17)Menor preço via Magazine LuizaR$ 1.999,00até 10x de R$ 232,44\n            \n          Frete Grátis 8% de volta na loja todaCompare entre 7 lojas",
    "price": "R$ 1.999,00",
    "url": "https://www.zoom.com.br/notebook/notebook-lenovo-ideapad-1-82x5000abr-amd-ryzen-3-7320u-15-6-8gb-ssd-256-gb-windows-11?_lc=88&searchterm=notebook",
    "specifications": {}
  },
  {
    "rank": 266,
    "name": "Notebook Lenovo Ideapad 1 AMD Ryzen 3-7320U 15,6\" 8GB SSD 256GB Windows 11 82X5000ABR4.6 (17)Menor preço via Magazine LuizaR$ 1.999,00até 10x de R$ 232,44\n            \n          Frete Grátis 8% de volta na loja todaCompare entre 7 lojas",
    "price": "R$ 1.999,00",
    "url": "https://www.zoom.com.br/notebook/notebook-lenovo-ideapad-1-82x5000abr-amd-ryzen-3-7320u-15-6-8gb-ssd-256-gb-windows-11?_lc=88&searchterm=notebook",
    "specifications": {}
  },
  {
    "rank": 267,
    "name": "Sem título",
    "price": "Sem preço",
    "url": null,
    "specifications": {}
  },
  {
    "rank": 268,
    "name": "Sem título",
    "price": "Sem preço",
    "url": null,
    "specifications": {}
  },
  {
    "rank": 269,
    "name": "Notebook Lenovo Ideapad 1 AMD Ryzen 3-7320U 15,6\" 8GB SSD 256GB Windows 11 82X5000ABR",
    "price": "R$ 1.999,00",
    "url": null,
    "specifications": {}
  },
  {
    "rank": 270,
    "name": "Sem título",
    "price": "Sem preço",
    "url": null,
    "specifications": {}
  },
  {
    "rank": 271,
    "name": "Notebook Lenovo Ideapad 1 AMD Ryzen 3-7320U 15,6\" 8GB SSD 256GB Windows 11 82X5000ABR",
    "price": "R$ 1.999,00",
    "url": null,
    "specifications": {}
  },
  {
    "rank": 272,
    "name": "Notebook Lenovo Ideapad 1 AMD Ryzen 3-7320U 15,6\" 8GB SSD 256GB Windows 11 82X5000ABR",
    "price": "Sem preço",
    "url": null,
    "specifications": {}
  },
  {
    "rank": 273,
    "name": "Sem título",
    "price": "Sem preço",
    "url": null,
    "specifications": {}
  },
  {
    "rank": 274,
    "name": "Sem título",
    "price": "Sem preço",
    "url": null,
    "specifications": {}
  },
  {
    "rank": 275,
    "name": "Notebook Samsung Galaxy Book4 Intel Core i7-1355U 15,6\" 16GB SSD 512GB Windows 11 NP750XGJ-KG1BR4.5 (66)Menor preço via ExtraR$ 4.839,12até 10x de R$ 549,90\n            \n          Frete Grátis 5% de volta na loja todaCompare entre 3 lojas",
    "price": "R$ 4.839,12",
    "url": "https://www.zoom.com.br/notebook/notebook-samsung-book-np750xgj-kg1br-intel-core-i7-1355u-15-6-16gb-ssd-512-gb-windows-11?_lc=88&searchterm=notebook",
    "specifications": {}
  },
  {
    "rank": 276,
    "name": "Notebook Samsung Galaxy Book4 Intel Core i7-1355U 15,6\" 16GB SSD 512GB Windows 11 NP750XGJ-KG1BR4.5 (66)Menor preço via ExtraR$ 4.839,12até 10x de R$ 549,90\n            \n          Frete Grátis 5% de volta na loja todaCompare entre 3 lojas",
    "price": "R$ 4.839,12",
    "url": "https://www.zoom.com.br/notebook/notebook-samsung-book-np750xgj-kg1br-intel-core-i7-1355u-15-6-16gb-ssd-512-gb-windows-11?_lc=88&searchterm=notebook",
    "specifications": {}
  },
  {
    "rank": 277,
    "name": "Sem título",
    "price": "Sem preço",
    "url": null,
    "specifications": {}
  },
  {
    "rank": 278,
    "name": "Sem título",
    "price": "Sem preço",
    "url": null,
    "specifications": {}
  },
  {
    "rank": 279,
    "name": "Notebook Samsung Galaxy Book4 Intel Core i7-1355U 15,6\" 16GB SSD 512GB Windows 11 NP750XGJ-KG1BR",
    "price": "R$ 4.839,12",
    "url": null,
    "specifications": {}
  },
  {
    "rank": 280,
    "name": "Sem título",
    "price": "Sem preço",
    "url": null,
    "specifications": {}
  },
  {
    "rank": 281,
    "name": "Notebook Samsung Galaxy Book4 Intel Core i7-1355U 15,6\" 16GB SSD 512GB Windows 11 NP750XGJ-KG1BR",
    "price": "R$ 4.839,12",
    "url": null,
    "specifications": {}
  },
  {
    "rank": 282,
    "name": "Notebook Samsung Galaxy Book4 Intel Core i7-1355U 15,6\" 16GB SSD 512GB Windows 11 NP750XGJ-KG1BR",
    "price": "Sem preço",
    "url": null,
    "specifications": {}
  },
  {
    "rank": 283,
    "name": "Sem título",
    "price": "Sem preço",
    "url": null,
    "specifications": {}
  },
  {
    "rank": 284,
    "name": "Sem título",
    "price": "Sem preço",
    "url": null,
    "specifications": {}
  },
  {
    "rank": 285,
    "name": "Sem título",
    "price": "Sem preço",
    "url": null,
    "specifications": {}
  },
  {
    "rank": 286,
    "name": "Sem título",
    "price": "até R$ 86",
    "url": null,
    "specifications": {}
  },
  {
    "rank": 287,
    "name": "Sem título",
    "price": "até R$ 86",
    "url": null,
    "specifications": {}
  },
  {
    "rank": 288,
    "name": "Sem título",
    "price": "até R$ 86",
    "url": null,
    "specifications": {}
  },
  {
    "rank": 289,
    "name": "Sem título",
    "price": "R$ 86 a R$ 109",
    "url": null,
    "specifications": {}
  },
  {
    "rank": 290,
    "name": "Sem título",
    "price": "mais de R$ 109",
    "url": null,
    "specifications": {}
  },
  {
    "rank": 291,
    "name": "IndicaProdutos indicados por Especialistas Zoom. (+100)",
    "price": "Sem preço",
    "url": "https://www.zoom.com.br/search?q=notebook&hitsPerPage=24&refinements%5B0%5D%5Bid%5D=stamps&refinements%5B0%5D%5Bvalues%5D%5B0%5D=EditorPick&sortBy=default&enableRefinementsSuggestions=true&isDealsPage=false",
    "specifications": {}
  },
  {
    "rank": 292,
    "name": "Sem título",
    "price": "Sem preço",
    "url": null,
    "specifications": {}
  },
  {
    "rank": 293,
    "name": "Sem título",
    "price": "Sem preço",
    "url": null,
    "specifications": {}
  },
  {
    "rank": 294,
    "name": "#praeditarvideo(26)",
    "price": "Sem preço",
    "url": "https://www.zoom.com.br/search?q=notebook&hitsPerPage=24&refinements%5B0%5D%5Bid%5D=productTags.EDITORIAL&refinements%5B0%5D%5Bvalues%5D%5B0%5D=pra-editar-video&sortBy=default&enableRefinementsSuggestions=true&isDealsPage=false",
    "specifications": {}
  },
  {
    "rank": 295,
    "name": "Amazon(+100)",
    "price": "Sem preço",
    "url": "https://www.zoom.com.br/search?q=notebook&hitsPerPage=24&refinements%5B0%5D%5Bid%5D=bestSellingMerchantName&refinements%5B0%5D%5Bvalues%5D%5B0%5D=Amazon&sortBy=default&enableRefinementsSuggestions=true&isDealsPage=false",
    "specifications": {}
  },
  {
    "rank": 296,
    "name": "Todas(+100)",
    "price": "Sem preço",
    "url": "https://www.zoom.com.br/search?q=notebook&hitsPerPage=24&refinements%5B0%5D%5Bid%5D=rating&refinements%5B0%5D%5Branges%5D%5Bmin%5D=0&sortBy=default&isDealsPage=false&enableRefinementsSuggestions=true",
    "specifications": {}
  },
  {
    "rank": 297,
    "name": "Todas(+100)",
    "price": "Sem preço",
    "url": "https://www.zoom.com.br/search?q=notebook&hitsPerPage=24&refinements%5B0%5D%5Bid%5D=rating&refinements%5B0%5D%5Branges%5D%5Bmin%5D=0&sortBy=default&isDealsPage=false&enableRefinementsSuggestions=true",
    "specifications": {}
  },
  {
    "rank": 298,
    "name": "Tire sua dúvida",
    "price": "Sem preço",
    "url": "https://tiresuaduvida.zoom.com.br",
    "specifications": {}
  },
  {
    "rank": 299,
    "name": "",
    "price": "Sem preço",
    "url": "https://www.reclameaqui.com.br/premio/votacao/servicos/154/",
    "specifications": {}
  }
]